anime_seg/__init__.py
anime_seg/example.py
anime_seg/model.py
anime_seg/pipeline.py
anime_seg-0.1.5.dist-info/METADATA
anime_seg-0.1.5.dist-info/WHEEL
anime_seg-0.1.5.dist-info/top_level.txt
anime_seg-0.1.5.dist-info/RECORD
