Metadata-Version: 2.4
Name: anime_seg
Version: 0.1.5
Summary: Anime Character Segmentation with DINOv2
Home-page: https://github.com/suzukimain/AnimeSeg
Author: suzukimain
Author-email: gt13579552@gmail.com
Classifier: Programming Language :: Python :: 3
Classifier: Operating System :: OS Independent
Requires-Python: >=3.8
Requires-Dist: torch>=2.0.0
Requires-Dist: numpy
Requires-Dist: Pillow
Requires-Dist: transformers
Requires-Dist: huggingface_hub
Requires-Dist: safetensors
Requires-Dist: peft
Dynamic: author
Dynamic: author-email
Dynamic: classifier
Dynamic: description
Dynamic: description-content-type
Dynamic: home-page
Dynamic: requires-dist
Dynamic: requires-python
Dynamic: summary
